MANIFEST.in
README.md
setup.py
geeklish/__init__.py
geeklish/adjective.py
geeklish/adverb.py
geeklish/clause.py
geeklish/conjunction.py
geeklish/noun.py
geeklish/others.py
geeklish/preposition.py
geeklish/verb.py
geeklish.egg-info/PKG-INFO
geeklish.egg-info/SOURCES.txt
geeklish.egg-info/dependency_links.txt
geeklish.egg-info/not-zip-safe
geeklish.egg-info/top_level.txt
geeklish/dictionary/.DS_Store
geeklish/dictionary/adjectives.json
geeklish/dictionary/adverbs.json
geeklish/dictionary/conjunctions.json
geeklish/dictionary/prepositions.json
geeklish/dictionary/nouns/determiners.json
geeklish/dictionary/nouns/nouns.json
geeklish/dictionary/nouns/pronouns.json
geeklish/dictionary/verbs/modals.json
geeklish/dictionary/verbs/verbs.json