Metadata-Version: 1.0
Name: geeklish
Version: 0.1.0
Summary: Learn English by Coding
Home-page: http://github.com/kenzotakahashi/geeklish
Author: Kenzo Takahashi
Author-email: kenzotakahashi2@gmail.com
License: MIT
Platform: UNKNOWN
